js.q-1.0.1-py2.7-nspkg.pth
js/q/__init__.py
js/q/test_q.txt
js/q/resources/q.js
js.q-1.0.1.dist-info/DESCRIPTION.rst
js.q-1.0.1.dist-info/entry_points.txt
js.q-1.0.1.dist-info/METADATA
js.q-1.0.1.dist-info/metadata.json
js.q-1.0.1.dist-info/namespace_packages.txt
js.q-1.0.1.dist-info/RECORD
js.q-1.0.1.dist-info/top_level.txt
js.q-1.0.1.dist-info/WHEEL
