Metadata-Version: 2.0
Name: js.q
Version: 1.0.1
Summary: Fanstatic packaging of q
Home-page: https://bitbucket.org/negval/js.q
Author: Denis Sukhonin
Author-email: d.sukhonin@gmail.com
License: BSD
Keywords: fanstatic js javascript q
Platform: UNKNOWN
Requires-Dist: fanstatic
Requires-Dist: setuptools
